[
	{
		"fileName":"1.jpg",
		"title":"1",
		"desc":"a beautiful day one"
	},{
		"fileName":"2.jpg",
		"title":"2",
		"desc":"a beautiful day two"
	},{
		"fileName":"3.jpg",
		"title":"3",
		"desc":"a beautiful day three"
	},{
		"fileName":"4.jpg",
		"title":"4",
		"desc":"a beautiful day four"
	},{
		"fileName":"5.jpg",
		"title":"5",
		"desc":"a beautiful day five"
	},{
		"fileName":"6.jpg",
		"title":"6",
		"desc":"a beautiful day six"
	},{
		"fileName":"7.jpg",
		"title":"7",
		"desc":"a beautiful day seven"
	},{
		"fileName":"8.jpg",
		"title":"8",
		"desc":"a beautiful day eight"
	},{
		"fileName":"9.jpg",
		"title":"9",
		"desc":"a beautiful day nine"
	},{
		"fileName":"10.jpg",
		"title":"10",
		"desc":"a beautiful day ten"
	},{
		"fileName":"11.jpg",
		"title":"11",
		"desc":"a beautiful day eleven"
	},{
		"fileName":"12.jpg",
		"title":"12",
		"desc":"a beautiful day twelve"
	},{
		"fileName":"13.jpg",
		"title":"13",
		"desc":"a beautiful day thirteen"
	},{
		"fileName":"14.jpg",
		"title":"14",
		"desc":"a beautiful day fourthteen"
	},{
		"fileName":"15.jpg",
		"title":"15",
		"desc":"a beautiful day fifteen"
	},
]